aghast/__init__.py
aghast/checktype.py
aghast/interface.py
aghast/version.py
aghast/_connect/__init__.py
aghast/_connect/_fnalhist.py
aghast/_connect/_numpy.py
aghast/_connect/_pandas.py
aghast/_connect/_root.py
aghast/aghast_generated/Assignment.py
aghast/aghast_generated/Axis.py
aghast/aghast_generated/BinLocation.py
aghast/aghast_generated/BinnedEvaluatedFunction.py
aghast/aghast_generated/Binning.py
aghast/aghast_generated/CategoryBinning.py
aghast/aghast_generated/Chunk.py
aghast/aghast_generated/Collection.py
aghast/aghast_generated/Column.py
aghast/aghast_generated/ColumnChunk.py
aghast/aghast_generated/Counts.py
aghast/aghast_generated/Covariance.py
aghast/aghast_generated/DType.py
aghast/aghast_generated/Decoration.py
aghast/aghast_generated/DecorationLanguage.py
aghast/aghast_generated/DimensionOrder.py
aghast/aghast_generated/EdgesBinning.py
aghast/aghast_generated/Endianness.py
aghast/aghast_generated/EvaluatedFunction.py
aghast/aghast_generated/ExternalSource.py
aghast/aghast_generated/Extremes.py
aghast/aghast_generated/Filter.py
aghast/aghast_generated/FractionBinning.py
aghast/aghast_generated/FractionErrorMethod.py
aghast/aghast_generated/FractionLayout.py
aghast/aghast_generated/Function.py
aghast/aghast_generated/FunctionData.py
aghast/aghast_generated/FunctionObject.py
aghast/aghast_generated/FunctionObjectData.py
aghast/aghast_generated/HexagonalBinning.py
aghast/aghast_generated/HexagonalCoordinates.py
aghast/aghast_generated/Histogram.py
aghast/aghast_generated/IntegerBinning.py
aghast/aghast_generated/InterpretedBuffer.py
aghast/aghast_generated/InterpretedExternalBuffer.py
aghast/aghast_generated/InterpretedInlineBuffer.py
aghast/aghast_generated/InterpretedInlineFloat64Buffer.py
aghast/aghast_generated/InterpretedInlineInt64Buffer.py
aghast/aghast_generated/IrregularBinning.py
aghast/aghast_generated/Metadata.py
aghast/aghast_generated/MetadataLanguage.py
aghast/aghast_generated/Modes.py
aghast/aghast_generated/Moments.py
aghast-0.2.1.dist-info/METADATA
aghast-0.2.1.dist-info/WHEEL
aghast-0.2.1.dist-info/top_level.txt
aghast-0.2.1.dist-info/RECORD
