Metadata-Version: 2.1
Name: aghast
Version: 0.2.1
Summary: Aghast: aggregated, histogram-like statistics, sharable as Flatbuffers.
Home-page: https://github.com/scikit-hep/aghast
Author: Jim Pivarski (IRIS-HEP)
Author-email: pivarski@princeton.edu
Maintainer: Jim Pivarski (IRIS-HEP)
Maintainer-email: pivarski@princeton.edu
License: BSD 3-clause
Download-URL: https://github.com/scikit-hep/aghast/releases
Platform: Any
Classifier: Development Status :: 4 - Beta
Classifier: Intended Audience :: Developers
Classifier: Intended Audience :: Information Technology
Classifier: Intended Audience :: Science/Research
Classifier: License :: OSI Approved :: BSD License
Classifier: Operating System :: MacOS
Classifier: Operating System :: POSIX
Classifier: Operating System :: Unix
Classifier: Programming Language :: Python
Classifier: Programming Language :: Python :: 2.7
Classifier: Programming Language :: Python :: 3.4
Classifier: Programming Language :: Python :: 3.5
Classifier: Programming Language :: Python :: 3.6
Classifier: Programming Language :: Python :: 3.7
Classifier: Topic :: Scientific/Engineering
Classifier: Topic :: Scientific/Engineering :: Information Analysis
Classifier: Topic :: Scientific/Engineering :: Mathematics
Classifier: Topic :: Scientific/Engineering :: Physics
Classifier: Topic :: Software Development
Classifier: Topic :: Utilities
Requires-Dist: flatbuffers (>=1.8.0)
Requires-Dist: numpy
